ssh_authorizer
