Metadata-Version: 1.1
Name: ssh-authorizer
Version: 1.2
Summary: Manager for remote ~/.ssh/authorized_keys.
Home-page: https://github.com/zzzsochi/ssh-authorizer/
Author: Alexander Zelenyak aka ZZZ
Author-email: zzz.sochi@gmail.com
License: UNKNOWN
Platform: UNKNOWN
Classifier: Operating System :: Unix
Classifier: Programming Language :: Python :: 3
Classifier: Programming Language :: Python :: 3.3
